m203mylibrary/__init__.py
m203mylibrary/commodities_backtest.py
m203mylibrary/commodities_broker.py
m203mylibrary/commodities_data_module.py
m203mylibrary/m203mylibrary.py
m203mylibrary/multi_asset_backtest.py
m203mylibrary-0.1.3.dist-info/LICENSE
m203mylibrary-0.1.3.dist-info/METADATA
m203mylibrary-0.1.3.dist-info/WHEEL
m203mylibrary-0.1.3.dist-info/RECORD
