Metadata-Version: 2.1
Name: m203mylibrary
Version: 0.1.3
Summary: Library created for the m203 python project. It is adding new features to the library pybacktestchain
License: MIT
Author: Mehmet Basagac
Requires-Python: >=3.10.15,<4.0.0
Classifier: License :: OSI Approved :: MIT License
Classifier: Programming Language :: Python :: 3
Classifier: Programming Language :: Python :: 3.11
Classifier: Programming Language :: Python :: 3.12
Classifier: Programming Language :: Python :: 3.13
Requires-Dist: numba (>=0.60.0,<0.61.0)
Requires-Dist: pybacktestchain (>=0.2.1,<0.3.0)
